python_project_2026/__init__.py
python_project_2026/main.py
python_project_2026/utils.py
python_project_2026-0.2.0.dist-info/METADATA
python_project_2026-0.2.0.dist-info/WHEEL
python_project_2026-0.2.0.dist-info/entry_points.txt
python_project_2026-0.2.0.dist-info/licenses/LICENSE
python_project_2026-0.2.0.dist-info/RECORD
