Metadata-Version: 2.4
Name: python-project-2026
Version: 0.2.0
Summary: 2026年の最新Python開発テンプレート
Project-URL: Homepage, https://github.com/username/python-project-2026
Project-URL: Repository, https://github.com/username/python-project-2026
Project-URL: Documentation, https://username.github.io/python-project-2026
Project-URL: Issues, https://github.com/username/python-project-2026/issues
Author-email: Developer <dev@example.com>
License: MIT License
License-File: LICENSE
Keywords: modern,python,template
Classifier: Development Status :: 4 - Beta
Classifier: Intended Audience :: Developers
Classifier: License :: OSI Approved :: MIT License
Classifier: Programming Language :: Python :: 3
Classifier: Programming Language :: Python :: 3.12
Classifier: Programming Language :: Python :: 3.13
Requires-Python: >=3.12
Requires-Dist: httpx>=0.25.0
Requires-Dist: pydantic>=2.5.0
Requires-Dist: rich>=13.0.0
Requires-Dist: typer>=0.9.0
